mdict.py
setup.py
mdict.egg-info/PKG-INFO
mdict.egg-info/SOURCES.txt
mdict.egg-info/dependency_links.txt
mdict.egg-info/top_level.txt