Metadata-Version: 1.0
Name: mdict
Version: 1.0.2
Summary: mdict is a utility for robustly retrieving and storing values in nested python dicts.
Home-page: https://github.com/rikonor/mdict
Author: Or Rikon
Author-email: rikonor@gmail.com
License: MIT
Keywords: dict
Platform: UNKNOWN
